arclet/alconna/tools/__init__.py
arclet/alconna/tools/actions.py
arclet/alconna/tools/checker.py
arclet/alconna/tools/construct.py
arclet/alconna/tools/debug.py
arclet/alconna/tools/formatter.py
arclet/alconna/tools/i18n/.config.json
arclet/alconna/tools/i18n/.lang.schema.json
arclet/alconna/tools/i18n/.template.json
arclet/alconna/tools/i18n/.template.schema.json
arclet/alconna/tools/i18n/__init__.py
arclet/alconna/tools/i18n/en-US.json
arclet/alconna/tools/i18n/zh-CN.json
arclet/alconna/tools/pattern.py
arclet_alconna_tools-0.7.12.dist-info/METADATA
arclet_alconna_tools-0.7.12.dist-info/WHEEL
arclet_alconna_tools-0.7.12.dist-info/entry_points.txt
arclet_alconna_tools-0.7.12.dist-info/licenses/LICENSE
arclet_alconna_tools-0.7.12.dist-info/RECORD
