Metadata-Version: 2.1
Name: arclet-alconna-tools
Version: 0.7.12
Summary: Builtin Tools for Alconna
Author-Email: RF-Tar-Railt <rf_tar_railt@qq.com>
License: MIT
Requires-Python: >=3.9
Requires-Dist: nepattern<1.0.0,>=0.7.3
Requires-Dist: arclet-alconna>=1.8.43
